{"cameraMode":{"drawMode":0,"name":"Shaded","section":"Shading Mode"},"sceneLighting":true,"audioPlay":false,"sceneViewState":{"m_AlwaysRefresh":false,"showFog":true,"showSkybox":true,"showFlares":true,"showImageEffects":true,"showParticleSystems":true,"showVisualEffectGraphs":true,"m_FxEnabled":true},"in2DMode":false,"pivot":{"x":134.29812622070313,"y":259.4491882324219,"z":7.871103286743164},"rotation":{"x":0.7017828822135925,"y":-0.0010685849701985717,"z":0.0010526751866564155,"w":0.712389349937439},"size":-1.5893280506134034,"orthographic":false}